ipymafs/.DS_Store
ipymafs/__init__.py
ipymafs/bezier.css
ipymafs/bezier.js
ipymafs/ellipse.css
ipymafs/ellipse.js
ipymafs/line.css
ipymafs/line.js
ipymafs-0.1.0.dist-info/METADATA
ipymafs-0.1.0.dist-info/WHEEL
ipymafs-0.1.0.dist-info/RECORD
