Metadata-Version: 2.1
Name: ipymafs
Version: 0.1.0
License-Expression: MIT
Requires-Dist: anywidget
Provides-Extra: dev
Requires-Dist: jupyterlab; extra == 'dev'
Requires-Dist: watchfiles; extra == 'dev'
